{"type": "Feature", "id": 12522966, "properties": {"woe:id": 12522966, "woe:parent_id": 1252654, "woe:name": "Van Canh Airport", "woe:placetype": 14, "woe:placetype_name": "Airport", "woe:lang": "ENG", "iso:country": "VN", "meta:provider": ["geoplanet:7.3.1", "geoplanet:7.3.2", "geoplanet:7.4.0", "geoplanet:7.4.1", "geoplanet:7.5.1", "geoplanet:7.5.2", "geoplanet:7.6.0", "geoplanet:7.8.1", "geoplanet:7.9.0", "geoplanet:7.10.0", "geoplanet:8.0.0", "woeplanet:8.0.0"], "meta:indexed": "2020-08-20T20:27:34.071327", "meta:updated": "2020-08-22T01:58:49.737836", "woe:hierarchy": {"continent": 24865671, "country": 23424984, "town": 0, "planet": 1, "county": 0, "suburb": 0, "state": 2347730, "region": 0, "localadmin": 0}, "woe:timezone_id": 28350852, "woe:hash": "w6mmxbmud9me", "woe:centroid": [108.9814, 13.6252], "geom:latitude": 13.6252, "geom:longitude": 108.9814, "geom:hash": "w6mmxbmud9me", "woe:latitude": 13.6252, "geom:centroid": [108.9814, 13.6252], "woe:longitude": 108.9814, "woe:repo": "woeplanet-airport-vn"}, "geometry": {"coordinates": [108.9814, 13.6252], "type": "Point"}}