{"type": "Feature", "id": 12522947, "properties": {"woe:id": 12522947, "woe:parent_id": 1252568, "woe:name": "Pleiku Area Airport", "woe:placetype": 14, "woe:placetype_name": "Airport", "woe:lang": "ENG", "iso:country": "VN", "meta:provider": ["geoplanet:7.3.1", "geoplanet:7.3.2", "geoplanet:7.4.0", "geoplanet:7.4.1", "geoplanet:7.5.1", "geoplanet:7.5.2", "geoplanet:7.6.0", "geoplanet:7.8.1", "geoplanet:7.9.0", "geoplanet:7.10.0", "geoplanet:8.0.0", "woeplanet:8.0.0"], "meta:indexed": "2020-08-20T20:27:34.054949", "woe:alias_ENG_V": ["PXU Airport", "PXU", "Pleiku Area"], "meta:updated": "2020-08-22T01:58:49.732331", "woe:hierarchy": {"continent": 24865671, "country": 23424984, "town": 0, "planet": 1, "county": 0, "suburb": 0, "state": 2347733, "region": 0, "localadmin": 0}, "woe:timezone_id": 28350852, "woe:hash": "w6kzd80bt0uu", "woe:centroid": [108.040802, 13.9747], "geom:latitude": 13.9747, "geom:longitude": 108.040802, "geom:hash": "w6kzd80bt0uu", "woe:latitude": 13.9747, "geom:centroid": [108.040802, 13.9747], "woe:longitude": 108.040802, "woe:repo": "woeplanet-airport-vn"}, "geometry": {"coordinates": [108.040802, 13.9747], "type": "Point"}}