{"type": "Feature", "id": 12522907, "geometry": {"type": "Point", "coordinates": [103.958, 10.2233]}, "properties": {"woe:id": 12522907, "woe:parent_id": 1244351, "woe:name": "Duong Dong Airport", "woe:placetype": 14, "woe:placetype_name": "Airport", "woe:lang": "ENG", "iso:country": "VN", "meta:provider": ["geoplanet:7.3.1", "geoplanet:7.3.2", "geoplanet:7.4.0", "geoplanet:7.4.1", "geoplanet:7.5.1", "geoplanet:7.5.2", "geoplanet:7.6.0", "geoplanet:7.8.1", "geoplanet:7.9.0", "geoplanet:7.10.0", "geoplanet:8.0.0", "woeplanet:8.0.0"], "meta:indexed": "2020-08-20T20:27:34.021362", "woe:alias_ENG_V": ["PQC Airport", "PQC"], "meta:updated": "2020-10-14T11:40:20.241292", "woe:hierarchy": {"continent": 24865671, "country": 23424984, "town": 0, "planet": 1, "county": 0, "suburb": 0, "state": 2347723, "region": 0, "localadmin": 0}, "woe:timezone_id": 28350852, "woe:hash": "w3cfjt5ghcpp", "woe:centroid": [103.958, 10.2233], "geom:latitude": 10.2233, "geom:longitude": 103.958, "geom:hash": "w3cfjt5ghcpp", "woe:latitude": 10.2233, "geom:centroid": [103.958, 10.2233], "woe:longitude": 103.958, "woe:repo": "woeplanet-airport-vn", "geom:area": 0.0, "woe:scale": 19}}