{"type": "Feature", "id": 12522935, "geometry": {"type": "Point", "coordinates": [104.9832, 8.7546]}, "properties": {"woe:id": 12522935, "woe:parent_id": 1252707, "woe:name": "Nam Can Airport", "woe:placetype": 14, "woe:placetype_name": "Airport", "woe:lang": "ENG", "iso:country": "VN", "meta:provider": ["geoplanet:7.3.1", "geoplanet:7.3.2", "geoplanet:7.4.0", "geoplanet:7.4.1", "geoplanet:7.5.1", "geoplanet:7.5.2", "geoplanet:7.6.0", "geoplanet:7.8.1", "geoplanet:7.9.0", "geoplanet:7.10.0", "geoplanet:8.0.0", "woeplanet:8.0.0"], "meta:indexed": "2020-08-20T20:27:34.044675", "meta:updated": "2020-10-14T11:40:20.240252", "woe:hierarchy": {"continent": 24865671, "country": 23424984, "town": 0, "planet": 1, "county": 0, "suburb": 0, "state": 20070082, "region": 0, "localadmin": 0}, "woe:timezone_id": 28350852, "woe:hash": "w3d9ucwrjzex", "woe:centroid": [104.9832, 8.7546], "geom:latitude": 8.7546, "geom:longitude": 104.9832, "geom:hash": "w3d9ucwrjzex", "woe:latitude": 8.7546, "geom:centroid": [104.9832, 8.7546], "woe:longitude": 104.9832, "woe:repo": "woeplanet-airport-vn", "geom:area": 0.0, "woe:scale": 19}}